{
    "control_positions": {
        "1M": {
            "callsign": "I90_DEP",
            "frequency": 132250,
            "radio_name": "Houston Departure"
        },
        "1R": {
            "callsign": "I90_R_APP",
            "frequency": 119700,
            "radio_name": "Houston Approach"
        },
        "1P": {
            "callsign": "I90_P_APP",
            "frequency": 123800,
            "radio_name": "Houston Approach"
        },
        "1N": {
            "callsign": "I90_N_APP",
            "frequency": 124350,
            "radio_name": "Houston Approach"
        },
        "1X": {
            "callsign": "I90_X_APP",
            "frequency": 119175,
            "radio_name": "Houston Approach"
        },
        "1U": {
            "callsign": "I90_U_APP",
            "frequency": 134300,
            "radio_name": "Houston Approach"
        },
        "1T": {
            "callsign": "I90_T_APP",
            "frequency": 127475,
            "radio_name": "Houston Approach"
        },
        "1Z": {
            "callsign": "I90_Z_APP",
            "frequency": 124225,
            "radio_name": "Houston Approach"
        },
        "1B": {
            "callsign": "I90_B_APP",
            "frequency": 134450,
            "radio_name": "Houston Approach"
        },
        "1J": {
            "callsign": "I90_J_APP",
            "frequency": 121300,
            "radio_name": "Houston Approach"
        },
        "1D": {
            "callsign": "I90_D_APP",
            "frequency": 120050,
            "radio_name": "Houston Approach"
        },
        "1G": {
            "callsign": "I90_G_APP",
            "frequency": 119625,
            "radio_name": "Houston Approach"
        },
        "1H": {
            "callsign": "I90_H_APP",
            "frequency": 133050,
            "radio_name": "Houston Approach"
        },
        "1A": {
            "callsign": "I90_A_APP",
            "frequency": 119100,
            "radio_name": "Houston Approach"
        },
        "1I": {
            "callsign": "I90_I_APP",
            "frequency": 120650,
            "radio_name": "Houston Approach"
        },
        "1O": {
            "callsign": "I90_O_APP",
            "frequency": 134000,
            "radio_name": "Houston Approach"
        },
        "4Z": {
            "callsign": "IAH_C_TWR",
            "frequency": 125350,
            "radio_name": "Houston Tower"
        },
        "4O": {
            "callsign": "HOU_TWR",
            "frequency": 118700,
            "radio_name": "Hobby Tower"
        },
        "4S": {
            "callsign": "SGR_TWR",
            "frequency": 118650,
            "radio_name": "Sugar Land Tower"
        },
        "4Q": {
            "callsign": "DWH_TWR",
            "frequency": 118400,
            "radio_name": "Hooks Tower"
        },
        "4V": {
            "callsign": "CXO_TWR",
            "frequency": 124125,
            "radio_name": "Conroe Tower"
        },
        "4L": {
            "callsign": "CLL_TWR",
            "frequency": 118500,
            "radio_name": "Easterwood Tower"
        },
        "3T": {
            "callsign": "BPT_TWR",
            "frequency": 119500,
            "radio_name": "Beaumont Tower"
        },
        "4G": {
            "callsign": "GLS_TWR",
            "frequency": 120575,
            "radio_name": "Galveston Tower"
        }
    },
    "config": {
        "configurations": {
            "STD": {
                "inbound_assignments": {
                    "BAYYY5": "1G",
                    "BELLR5": "1X",
                    "CESAN4": "1D",
                    "DOOBI2": "1D",
                    "DRLLR5": "1N",
                    "GESNR1": "1D",
                    "GUSHR3": "1N",
                    "HTOWN3": "1X",
                    "KIDDZ4": "1X",
                    "LINKK1": "1G",
                    "MSCOT4": "1N",
                    "NNCEE2": "1G",
                    "SKNRD4": "1D",
                    "TEJAS5": "1X",
                    "TKNIQ3": "1X",
                    "TTORO3": "1N",
                    "WAPPL6": "1D"
                },
                "departure_assignments": {
                    "KGLS": "1B",
                    "KHOU": "1M",
                    "KIAH": "1M",
                    "KSGR": "1P"
                },
                "default_consolidation": {
                    "1B": [
                        "1M",
                        "1D",
                        "1G",
                        "1N",
                        "1P",
                        "1X"
                    ]
                }
            },
            "IAH": {
                "inbound_assignments": {
                    "FINALSNE": "1I",
                    "FINALSNW": "1A",
                    "FINALSSE": "1O",
                    "FINALSSW": "1O"
                },
                "default_consolidation": {
                    "1A": [
                        "1I",
                        "1O"
                    ]
                }
            }
        },
        "center": "KIAH",
        "radar_sites": {
            "I90": {
                "char": "A",
                "position": "KIAH",
                "elevation": 96,
                "primary_range": 150,
                "secondary_range": 200,
                "silence_angle": 30,
                "slope_angle": 0.3
            }
        },
        "filters": {
            "inhibit_ca": [
                {
                    "id": "E NOCA",
                    "description": "IAH EAST CONFLICT SUPPRESSION",
                    "type": "polygon",
                    "floor": 0,
                    "ceiling": 7000,
                    "vertices": [
                        "N029.50.70.000,W095.53.72.000",
                        "N029.50.28.000,W095.20.32.000",
                        "N030.07.41.000,W095.19.93.000",
                        "N030.07.91.000,W095.53.19.000",
                        "N029.50.70.000,W095.53.72.000"
                    ]
                },
                {
                    "id": "W NOCA",
                    "description": "IAH WEST CONFLICT SUPPRESSION",
                    "type": "polygon",
                    "floor": 0,
                    "ceiling": 7000,
                    "vertices": [
                        "N029.50.28.000,W095.20.32.000",
                        "N030.07.41.000,W095.19.93.000",
                        "N030.07.41.000,W094.48.46.000",
                        "N029.50.36.000,W094.47.58.000",
                        "N029.50.28.000,W095.20.32.000"
                    ]
                }
            ]
        },
        "scratchpads": {
            "CRP": "FRE",
            "CRGER": "PRA",
            "PSTUR": "PRA",
            "WWREN": "AGG",
            "GUSTI": "TRI",
            "SPINY": "TRI",
            "TPAKK": "CLE",
            "NGP": "AGG",
            "LLA": "TRI",
            "SBI": "TRI",
            "WAILN": "PRA",
            "WEEED": "PRA",
            "LCH": "TRI",
            "BLING": "TRI",
            "HAWES": "CLE",
            "DPATY": "CLE",
            "DOLEY": "GOM",
            "CRIED": "GOM",
            "SAT": "PRA",
            "MNURE": "PRA",
            "MUSYL": "BOL",
            "HRV": "BOL",
            "MAJKK": "GOM",
            "JCT": "PRA"
        },
        "significant_points": {
            "BLING": {},
            "CRGER": {},
            "CRIED": {},
            "CRP": {},
            "DOLEY": {},
            "DPATY": {},
            "GUSTI": {},
            "HAWES": {},
            "HRV": {},
            "JCT": {},
            "LCH": {},
            "LLA": {},
            "MAJKK": {},
            "MNURE": {},
            "MUSYL": {},
            "NGP": {},
            "PSTUR": {},
            "SAT": {},
            "SBI": {},
            "SPINY": {},
            "TPAKK": {},
            "WAILN": {},
            "WEEED": {},
            "WWREN": {}
        },
        "video_map_file": "videomaps/ZHU-videomaps.gob.zst",
        "coordination_fixes": {
            "BEATL": [
                {
                    "type": "route",
                    "to": "I90",
                    "from": "ZHU"
                }
            ],
            "GILLL": [
                {
                    "type": "route",
                    "to": "I90",
                    "from": "ZHU"
                }
            ],
            "HOWLN": [
                {
                    "type": "route",
                    "to": "I90",
                    "from": "ZHU"
                }
            ],
            "BOPPR": [
                {
                    "type": "route",
                    "to": "I90",
                    "from": "ZHU"
                }
            ],
            "DOMNO": [
                {
                    "type": "route",
                    "to": "I90",
                    "from": "ZHU"
                }
            ],
            "SSTAX": [
                {
                    "type": "route",
                    "to": "I90",
                    "from": "ZHU"
                }
            ],
            "ZEEKK": [
                {
                    "type": "route",
                    "to": "I90",
                    "from": "ZHU"
                }
            ],
            "WUUDZ": [
                {
                    "type": "route",
                    "to": "I90",
                    "from": "ZHU"
                }
            ],
            "CATTT": [
                {
                    "type": "route",
                    "to": "I90",
                    "from": "ZHU"
                }
            ],
            "BBQUE": [
                {
                    "type": "route",
                    "to": "I90",
                    "from": "ZHU"
                }
            ],
            "JJACK": [
                {
                    "type": "route",
                    "to": "I90",
                    "from": "ZHU"
                }
            ],
            "BAYYY": [
                {
                    "type": "route",
                    "to": "I90",
                    "from": "ZHU"
                }
            ],
            "BELLR": [
                {
                    "type": "route",
                    "to": "I90",
                    "from": "ZHU"
                }
            ],
            "CAASE": [
                {
                    "type": "route",
                    "to": "I90",
                    "from": "ZHU"
                }
            ],
            "CESAN": [
                {
                    "type": "route",
                    "to": "I90",
                    "from": "ZHU"
                }
            ],
            "TKNIQ": [
                {
                    "type": "route",
                    "to": "I90",
                    "from": "ZHU"
                }
            ],
            "WAPPL": [
                {
                    "type": "route",
                    "to": "I90",
                    "from": "ZHU"
                }
            ]
        },
        "area_configs": {
            "1": {
                "video_maps": [
                    "I90 BASE MAP",
                    "I90 MVA FUS 3",
                    "I90 CLASS B",
                    "I90 MVA FUS 3",
                    "IAH FINAL EAST FLOW",
                    "IAH FINAL EAST FLOW ALT",
                    "IAH FINAL WEST FLOW",
                    "IAH FINAL WEST FLOW ALT",
                    "HOU FINAL 4",
                    "HOU FINAL EAST HOU 13 ALT",
                    "HOU FINAL WEST-15-33 HOU 13 ALT",
                    "CLASS D AIRPORTS",
                    "BPT EAST 15-33 HOU ALL",
                    "BPT WEST-15 HOU ALL",
                    "CLL-IDU EAST HOU ALL",
                    "CLL-IDU WEST-15-33 HOU ALL",
                    "DWH FINAL"
                ]
            }
        }
    },
    "handoff_ids": [
        {
            "id": "ACT",
            "prefix": "2"
        },
        {
            "id": "AUS",
            "prefix": "4"
        },
        {
            "id": "GRK",
            "prefix": "3"
        },
        {
            "id": "LCH",
            "prefix": "1"
        },
        {
            "id": "ZFW",
            "prefix": "F"
        },
        {
            "id": "ZHU",
            "prefix": "C"
        }
    ]
}
